ztestupload/__init__.py
ztestupload/add.py
ztestupload-0.0.1.dist-info/METADATA
ztestupload-0.0.1.dist-info/WHEEL
ztestupload-0.0.1.dist-info/top_level.txt
ztestupload-0.0.1.dist-info/RECORD
