Metadata-Version: 2.1
Name: ztestupload
Version: 0.0.1
Summary: upload test
Author: ZuoYihan
Classifier: Programming Language :: Python :: 3
Classifier: License :: OSI Approved :: MIT License
Classifier: Operating System :: OS Independent
